{"id":"313a3c62-266e-43da-9898-db27566e6a9a","timestamp":1751143532032,"matcher":{"static":{},"wildcard":{},"dynamic":{}},"prerendered":["/","/Portfolio","/ForSale","/Bio","/Login","/Admin/Bio","/Admin/Contact","/Stuff","/Admin/Stuff","/Admin/ForSale","/ForSale/Stuff","/ForSale/Clocks","/Portfolio/Film","/Portfolio/Truck","/Portfolio/Clocks","/Portfolio/Videos","/ForSale/Memorabilia","/Admin/Portfolio/Truck","/Portfolio/Machinery","/Admin/Portfolio","/Portfolio/Celebrities","/Admin/Portfolio/Celebs","/Admin/Portfolio/Clocks","/Admin/Portfolio/Videos","/Admin/Portfolio/Machinery","/Contact"]}