{"id":"d7858c25-815c-40df-951e-8d6ccf7e86b5","timestamp":1725486902138,"matcher":{"static":{},"wildcard":{},"dynamic":{}},"prerendered":["/","/Bio","/Portfolio","/ForSale","/Admin/Portfolio/Machinery","/Admin/Bio","/Admin/Portfolio/Celebs","/Admin/Contact","/Admin/ForSale","/Admin/Portfolio/Clocks","/Stuff","/Admin/Portfolio","/Admin/Portfolio/Videos","/Admin/Portfolio/Truck","/Admin/Stuff","/Login","/Portfolio/Film","/ForSale/Memorabilia","/ForSale/Clocks","/ForSale/Stuff","/Portfolio/Celebrities","/Portfolio/Clocks","/Portfolio/Machinery","/Portfolio/Truck","/Portfolio/Videos","/Contact"]}